aws_lambda_cli/__init__.py
aws_lambda_cli/__main__.py
aws_lambda_cli/build.py
aws_lambda_cli/cli/__init__.py
aws_lambda_cli/cli/configure.py
aws_lambda_cli/cli/function.py
aws_lambda_cli/cli/layer.py
aws_lambda_cli/cli/root.py
aws_lambda_cli/cli/utils.py
aws_lambda_cli/utils.py
aws_lambda_cli-0.2.0.dist-info/COPYING
aws_lambda_cli-0.2.0.dist-info/entry_points.txt
aws_lambda_cli-0.2.0.dist-info/METADATA
aws_lambda_cli-0.2.0.dist-info/WHEEL
aws_lambda_cli-0.2.0.dist-info/RECORD
