Metadata-Version: 2.1
Name: aws-lambda-cli
Version: 0.2.0
Summary: A simple CLI for building and publishing AWS Lambda functions.
Home-page: https://github.com/HassanAbouelela/aws-lambda-cli
License: GPL-3.0-or-later
Keywords: aws,lambda,serverless,botocore,boto3
Author: Hassan Abouelela
Author-email: hassan@hassanamr.com
Requires-Python: >=3.8,<4.0
Classifier: Development Status :: 4 - Beta
Classifier: Environment :: Console
Classifier: Intended Audience :: Developers
Classifier: License :: OSI Approved :: GNU General Public License v3 or later (GPLv3+)
Classifier: Operating System :: OS Independent
Classifier: Programming Language :: Python :: 3
Classifier: Programming Language :: Python :: 3.8
Classifier: Programming Language :: Python :: 3.9
Classifier: Programming Language :: Python :: 3.10
Classifier: Programming Language :: Python :: 3.11
Classifier: Programming Language :: Python :: 3.12
Requires-Dist: boto3 (>=1,<2)
Requires-Dist: click (>=8,<9)
Project-URL: Bug Tracker, https://github.com/HassanAbouelela/aws-lambda-cli/issues
Project-URL: Repository, https://github.com/HassanAbouelela/aws-lambda-cli
